kicoil/__init__.py
kicoil/cli.py
kicoil/geometry.py
kicoil/gui.py
kicoil/kicad.py
kicoil/skeleton.wasm
kicoil/skeletonator.py
kicoil/svg.py
kicoil-0.10.0.dist-info/WHEEL
kicoil-0.10.0.dist-info/entry_points.txt
kicoil-0.10.0.dist-info/METADATA
kicoil-0.10.0.dist-info/RECORD
