Metadata-Version: 2.4
Name: kicoil
Version: 0.10.0
Summary: Planar Inductor Generator
Keywords: kicad,gerber,pcb,electronics,EDA
Author: jaseg
License-Expression: Apache-2.0
Classifier: Development Status :: 5 - Production/Stable
Classifier: Environment :: Console
Classifier: Intended Audience :: Developers
Classifier: Intended Audience :: Information Technology
Classifier: Intended Audience :: Manufacturing
Classifier: Intended Audience :: Science/Research
Classifier: License :: OSI Approved :: Apache Software License
Classifier: Topic :: Multimedia :: Graphics
Classifier: Topic :: Scientific/Engineering
Classifier: Topic :: Scientific/Engineering :: Electronic Design Automation (EDA)
Classifier: Topic :: Utilities
Requires-Dist: beautifulsoup4>=4.14.3
Requires-Dist: click
Requires-Dist: gerbonara>=1.6.0
Requires-Dist: kicad-python>=0.5.0
Requires-Dist: lxml>=6.0.2
Requires-Dist: platformdirs>=4.5.1
Requires-Dist: py-straight-skeleton>=0.1.0
Requires-Dist: wasmtime>=39.0.0
Maintainer: Kicoil maintainers
Maintainer-email: Kicoil maintainers <kicoil@jaseg.de>
Requires-Python: >=3.13
Project-URL: Documentation, https://kicoil.jaseg.de/
Project-URL: Homepage, https://jaseg.de/projects/kicoil/
Project-URL: Source, https://git.jaseg.de/kicoil
Project-URL: Source Mirror, https://git.jaseg.de/kicoil.git
Project-URL: Tracker, https://codeberg.org/jaseg/kicoil/issues
